dictionary/__init__.py
dictionary/dictionary.py
berks_very_simple_dictionary-2.0.2.dist-info/METADATA
berks_very_simple_dictionary-2.0.2.dist-info/WHEEL
berks_very_simple_dictionary-2.0.2.dist-info/top_level.txt
berks_very_simple_dictionary-2.0.2.dist-info/RECORD
